prometheus_eval/__init__.py
prometheus_eval/judge.py
prometheus_eval/litellm.py
prometheus_eval/mock.py
prometheus_eval/parser.py
prometheus_eval/prompts.py
prometheus_eval/utils.py
prometheus_eval/vllm.py
prometheus_eval-0.1.20.dist-info/METADATA
prometheus_eval-0.1.20.dist-info/WHEEL
prometheus_eval-0.1.20.dist-info/RECORD
