Metadata-Version: 2.1
Name: prometheus-eval
Version: 0.1.20
Summary: A package for evaluating the performance of language models with Prometheus
Author: Juyoung Suk
Author-email: juyoung@kaist.ac.kr
Requires-Python: >=3.10,<4.0
Classifier: Programming Language :: Python :: 3
Classifier: Programming Language :: Python :: 3.10
Classifier: Programming Language :: Python :: 3.11
Classifier: Programming Language :: Python :: 3.12
Requires-Dist: aiolimiter (>=1.1.0,<2.0.0)
Requires-Dist: fastchat (>=0.1.0,<0.2.0)
Requires-Dist: litellm (>=1.40.0,<2.0.0)
